buildtool/__init__.py
buildtool/__main__.py
buildtool/build_coordinator.py
buildtool/build_worker.py
buildtool/cache.py
buildtool/context.py
buildtool/execution.py
buildtool/fs_utils.py
buildtool/loader.py
buildtool/monitoring.py
buildtool/preview_execution.py
buildtool/providers.py
buildtool/state.py
buildtool/utils.py
buildtool/work_queue.py
buildtool/workspace_setup.py
buildtool/common/__init__.py
buildtool/common/cli_utils.py
buildtool/common/course_config.py
buildtool/common/db.py
buildtool/common/hash_utils.py
buildtool/common/html.py
buildtool/common/jobs.py
buildtool/common/oauth_client.py
buildtool/common/permissions.py
buildtool/common/secrets.py
buildtool/common/shell_utils.py
buildtool/common/url_for.py
buildtool/common/rpc/__init__.py
buildtool/common/rpc/ag_master.py
buildtool/common/rpc/ag_worker.py
buildtool/common/rpc/auth.py
buildtool/common/rpc/auth_utils.py
buildtool/common/rpc/buildserver.py
buildtool/common/rpc/buildserver_hosted_worker.py
buildtool/common/rpc/code.py
buildtool/common/rpc/domains.py
buildtool/common/rpc/hosted.py
buildtool/common/rpc/howamidoing.py
buildtool/common/rpc/indexer.py
buildtool/common/rpc/mail.py
buildtool/common/rpc/oh.py
buildtool/common/rpc/paste.py
buildtool/common/rpc/sandbox.py
buildtool/common/rpc/search.py
buildtool/common/rpc/secrets.py
buildtool/common/rpc/sections.py
buildtool/common/rpc/slack.py
buildtool/common/rpc/utils.py
buildtool-0.2.9.dist-info/METADATA
buildtool-0.2.9.dist-info/WHEEL
buildtool-0.2.9.dist-info/entry_points.txt
buildtool-0.2.9.dist-info/top_level.txt
buildtool-0.2.9.dist-info/RECORD
