Metadata-Version: 2.1
Name: buildtool
Version: 0.2.9
Summary: UNKNOWN
Home-page: https://github.com/Cal-CS-61A-Staff/cs61a-apps/tree/master/buildtool
Author: Rahul Arya
Author-email: rahularya@berkeley.edu
License: MIT
Platform: UNKNOWN
Requires-Python: >=3.8
Requires-Dist: click
Requires-Dist: flask
Requires-Dist: cachetools
Requires-Dist: colorama
Requires-Dist: requests
Requires-Dist: tqdm
Requires-Dist: google-cloud-storage
Requires-Dist: packaging
Requires-Dist: pyyaml
Requires-Dist: syrupy
